pybaf/__init__.py
pybaf-2.0.0.dist-info/.gitignore
pybaf-2.0.0.dist-info/LICENSE
pybaf-2.0.0.dist-info/METADATA
pybaf-2.0.0.dist-info/WHEEL
pybaf-2.0.0.dist-info/top_level.txt
pybaf-2.0.0.dist-info/RECORD
