Metadata-Version: 2.1
Name: pybaf
Version: 2.0.0
Summary: Python Distance Calculator Bing Api facilitator
Home-page: https://github.com/joaovitocn/pybaf
Author: joaovitocn
Author-email: joaovitor.cn@gmail.com
License: UNKNOWN
Platform: UNKNOWN
Classifier: Programming Language :: Python :: 3
Classifier: Operating System :: OS Independent
Requires-Python: >=3.6
